py3collections-0.1.2.data/scripts/converter
py3collections-0.1.2.data/scripts/filefind
pycollections/__init__.py
pycollections/profiler.py
py3collections-0.1.2.dist-info/LICENCE
py3collections-0.1.2.dist-info/METADATA
py3collections-0.1.2.dist-info/WHEEL
py3collections-0.1.2.dist-info/entry_points.txt
py3collections-0.1.2.dist-info/top_level.txt
py3collections-0.1.2.dist-info/RECORD
